smtp_faker/__init__.py
smtp_faker/__main__.py
smtp_faker/db.py
smtp_faker/renderers.py
smtp_faker/smtpd.py
smtp_faker/static.py
smtp_faker/test.py
smtp_faker/views.py
smtp_faker/ws.py
smtp_faker/static/app.js
smtp_faker/static/favicon.ico
smtp_faker/static/index.html
smtp_faker/static/styles.css
smtp_faker-0.1.2.dist-info/METADATA
smtp_faker-0.1.2.dist-info/RECORD
smtp_faker-0.1.2.dist-info/WHEEL
smtp_faker-0.1.2.dist-info/entry_points.txt
smtp_faker-0.1.2.dist-info/top_level.txt
