Metadata-Version: 2.1
Name: smtp-faker
Version: 0.1.2
Summary: SMTP Faker -- smtp server for development
Home-page: https://github.com/zzzsochi/smtp-faker/
Author: UNKNOWN
Author-email: UNKNOWN
License: UNKNOWN
Keywords: asyncio,aiohttp,email,smtp,smtpd
Platform: UNKNOWN
Classifier: License :: OSI Approved :: BSD License
Classifier: Operating System :: POSIX
Classifier: Programming Language :: Python :: 3.6
Classifier: Topic :: Internet :: WWW/HTTP
Requires-Dist: aiohttp (>=3)
Requires-Dist: aiosmtpd
